flylog/__init__.py
flylog/constants.py
flylog/api/__init__.py
flylog/api/client.py
flylog/api/log_handler.py
flylog/server/__init__.py
flylog/server/log.py
flylog/server/server.py
flylog/server/six.py
flylog/server/utils.py
flylog/server/backends/__init__.py
flylog/server/backends/ding.py
flylog/server/backends/mail.py
flylog/server/backends/robot.py
flylog/server/backends/sendcloud.py
flylog_ding_robot-0.0.1.data/scripts/run_flylog.py
flylog_ding_robot-0.0.1.dist-info/METADATA
flylog_ding_robot-0.0.1.dist-info/WHEEL
flylog_ding_robot-0.0.1.dist-info/top_level.txt
flylog_ding_robot-0.0.1.dist-info/RECORD
