Metadata-Version: 2.1
Name: flylog-ding-robot
Version: 0.0.1
Summary: make log fly to mail or other or robot
Home-page: https://github.com/sbfksmq/flylog
Author: lijifeng
Author-email: sbfksmq@outlook.com
License: BSD
Platform: any
Requires-Dist: requests
